{
  "articles": [
    {
      "title": ""
    },
    {
      "title": ""
    },
    {
      "title": ""
    },
    {
      "title": ""
    },
    {
      "title": ""
    },
    {
      "title": "Rowan Atkinson"
    },
    {
      "title": "Matthew Broderick"
    },
    {
      "title": "Niketa Calame"
    },
    {
      "title": "Jim Cummings"
    },
    {
      "title": "Whoopi Goldberg"
    },
    {
      "title": "Robert Guillaume"
    },
    {
      "title": "Jeremy Irons"
    },
    {
      "title": "James Earl Jones"
    },
    {
      "title": "Moira Kelly"
    },
    {
      "title": "Nathan Lane"
    },
    {
      "title": "Zoe Leader"
    },
    {
      "title": "Cheech Marin"
    },
    {
      "title": "Ernie Sabella"
    },
    {
      "title": "Madge Sinclair"
    },
    {
      "title": "Jonathan Taylor Thomas"
    },
    {
      "title": ""
    },
    {
      "title": ""
    },
    {
      "title": ""
    },
    {
      "title": ""
    }
  ]
}
